{
  "produtos": [
    {
      "id": 1,
      "nome": "Sabão em Pó",
      "categoria": 1
    },
    {
      "id": 2,
      "nome": "Detergente",
      "categoria": 1
    },
    {
      "nome": "Amaciante",
      "categoria": "1",
      "id": 4
    },
    {
      "nome": "Alcatra",
      "categoria": "2",
      "id": 5
    },
    {
      "nome": "Picanha",
      "categoria": "2",
      "id": 6
    },
    {
      "id": 7,
      "nome": "Mouse",
      "categoria": "3"
    },
    {
      "nome": "Teclado",
      "categoria": "3",
      "id": 8
    },
    {
      "nome": "Papel Higiênico",
      "categoria": "1",
      "id": 9
    },
    {
      "nome": "Sabonete",
      "categoria": "1",
      "id": 14
    },
    {
      "nome": "Água",
      "categoria": "4",
      "id": 15
    }
  ],
  "categorias": [
    {
      "id": 1,
      "categoria": "Limpeza"
    },
    {
      "id": 2,
      "categoria": "Alimentos"
    },
    {
      "id": 3,
      "categoria": "Utilidades"
    },
    {
      "categoria": "Bebidas",
      "id": 4
    }
  ]
}